nehushtan/__init__.py
nehushtan/MessageQueue/NehushtanMessageQueue.py
nehushtan/MessageQueue/__init__.py
nehushtan/MessageQueue/implement/NehushtanMemoryMessageQueue.py
nehushtan/MessageQueue/implement/__init__.py
nehushtan/cli/ANSITerminalHelper.py
nehushtan/cli/CSISequence.py
nehushtan/cli/ISO6429.py
nehushtan/cli/NehushtanArgumentParser.py
nehushtan/cli/__init__.py
nehushtan/gui/__init__.py
nehushtan/gui/simple/SimpleWindow.py
nehushtan/gui/simple/__init__.py
nehushtan/gui/simple/constants/SimpleGuiTheme.py
nehushtan/gui/simple/constants/__init__.py
nehushtan/helper/CommonHelper.py
nehushtan/helper/SignalHandler.py
nehushtan/helper/__init__.py
nehushtan/helper/authenticate/TOTPKit.py
nehushtan/helper/authenticate/__init__.py
nehushtan/helper/io/CSVReader.py
nehushtan/helper/io/CSVReaderOptions.py
nehushtan/helper/io/CSVReaderRowHandleResult.py
nehushtan/helper/io/__init__.py
nehushtan/helper/timer/TimeCostHelper.py
nehushtan/helper/timer/TimeCostResult.py
nehushtan/helper/timer/__init__.py
nehushtan/httpd/NehushtanHTTPConstant.py
nehushtan/httpd/NehushtanHTTPRequestController.py
nehushtan/httpd/NehushtanHTTPRequestFilter.py
nehushtan/httpd/NehushtanHTTPRequestHandler.py
nehushtan/httpd/NehushtanHTTPResponseBuffer.py
nehushtan/httpd/NehushtanHTTPRoute.py
nehushtan/httpd/NehushtanHTTPRouter.py
nehushtan/httpd/NehushtanHTTPService.py
nehushtan/httpd/__init__.py
nehushtan/httpd/exceptions/NehushtanHTTPError.py
nehushtan/httpd/exceptions/NehushtanNoRouteMatchedError.py
nehushtan/httpd/exceptions/NehushtanRequestDeniedByFilterError.py
nehushtan/httpd/exceptions/NehushtanRequestParameterError.py
nehushtan/httpd/exceptions/NehushtanRequestProcessTargetError.py
nehushtan/httpd/exceptions/__init__.py
nehushtan/httpd/implement/NehushtanHTTPRouteWithRegexArgs.py
nehushtan/httpd/implement/NehushtanHTTPRouteWithRegexKwargs.py
nehushtan/httpd/implement/NehushtanHTTPRouteWithRestFul.py
nehushtan/httpd/implement/__init__.py
nehushtan/logger/AliyunSLSLoggerAdapter.py
nehushtan-0.5.16.dist-info/LICENSE
nehushtan-0.5.16.dist-info/METADATA
nehushtan-0.5.16.dist-info/WHEEL
nehushtan-0.5.16.dist-info/top_level.txt
nehushtan-0.5.16.dist-info/RECORD
