Metadata-Version: 2.1
Name: nehushtan
Version: 0.5.16
Summary: A toolkit for projects in Python
Home-page: https://sinri.github.io/nehushtan/
Author: Sinri Edogawa
Author-email: e.joshua.s.e@gmail.com
License: MIT
Classifier: Programming Language :: Python :: 3
Classifier: License :: OSI Approved :: MIT License
Classifier: Operating System :: OS Independent
Requires-Python: >=3.8
License-File: LICENSE
Requires-Dist: psutil~=6.0.0
